DkamSDK-1.4.87.data/purelib/DkamSDK/DkamSDK.dll
DkamSDK-1.4.87.data/purelib/DkamSDK/GCBase_MD_VC120_v3_1.dll
DkamSDK-1.4.87.data/purelib/DkamSDK/GenApi_MD_VC120_v3_1.dll
DkamSDK-1.4.87.data/purelib/DkamSDK/Log_MD_VC120_v3_1.dll
DkamSDK-1.4.87.data/purelib/DkamSDK/MathParser_MD_VC120_v3_1.dll
DkamSDK-1.4.87.data/purelib/DkamSDK/NodeMapData_MD_VC120_v3_1.dll
DkamSDK-1.4.87.data/purelib/DkamSDK/XmlParser_MD_VC120_v3_1.dll
DkamSDK-1.4.87.data/purelib/DkamSDK/_DkamSDK.cp37-win_amd64.pyd
DkamSDK-1.4.87.data/purelib/DkamSDK/__init__.py
DkamSDK-1.4.87.data/purelib/DkamSDK/clsercom.dll
DkamSDK-1.4.87.data/purelib/DkamSDK/sample/CaptureGrayImage.py
DkamSDK-1.4.87.data/purelib/DkamSDK/sample/CapturePointcloud.py
DkamSDK-1.4.87.data/purelib/DkamSDK/sample/CaptureRGBImage.py
DkamSDK-1.4.87.data/purelib/DkamSDK/sample/ConnectMultiplecameras.py
DkamSDK-1.4.87.data/purelib/DkamSDK/sample/Fusion3DToRGB.py
DkamSDK-1.4.87.data/purelib/DkamSDK/sample/GetCamInternelAndExternelParameter.py
DkamSDK-1.4.87.data/purelib/DkamSDK/sample/GetTimeStamp.py
DkamSDK-1.4.87.data/purelib/DkamSDK/sample/GetXmlNode.py
DkamSDK-1.4.87.data/purelib/DkamSDK/sample/ROIPixelMapping.py
DkamSDK-1.4.87.data/purelib/DkamSDK/sample/Test_all.py
DkamSDK-1.4.87.data/purelib/DkamSDK/sample/WriteOrReadRegister.py
DkamSDK-1.4.87.data/purelib/DkamSDK/sample/__init__.py
DkamSDK-1.4.87.dist-info/LICENSE
DkamSDK-1.4.87.dist-info/METADATA
DkamSDK-1.4.87.dist-info/WHEEL
DkamSDK-1.4.87.dist-info/top_level.txt
DkamSDK-1.4.87.dist-info/RECORD
