Metadata-Version: 2.1
Name: DkamSDK
Version: 1.4.87
Summary: Zhisensor Dkam
Home-page: UNKNOWN
Author: Zhisensor
Author-email: info@zhisensor.com
License: UNKNOWN
Download-URL: https://upload.pypi.org/legacy/
Keywords: dkam Dkam Zhisensor 3Dcamera
Platform: UNKNOWN
Requires-Dist: numpy (>=1.19.3)
